[
  {
    "time": "28/06/2026 09:13:01",
    "brand": "Abarth ES",
    "page": "Parcours",
    "type": "ko",
    "detail": "Très lent (5.28s)",
    "diagnostics": {
      "brand": "Abarth ES",
      "page": "Parcours",
      "http_status": 200,
      "elapsed_http": 5.28,
      "ip": [
        "135.125.7.226",
        0.002,
        null
      ],
      "error_type": "VERY_SLOW"
    },
    "screenshot": null,
    "is_reference": true
  },
  {
    "time": "28/06/2026 18:38:08",
    "brand": "Abarth ES",
    "page": "Parcours",
    "type": "recovery",
    "detail": "Retour en ligne",
    "is_reference": true
  }
]