[
  {
    "time": "05/07/2026 23:59:30",
    "brand": "Ford FR",
    "page": "Homepage",
    "type": "ko",
    "detail": "Pas de réponse après 2.55s",
    "diagnostics": {
      "brand": "Ford FR",
      "page": "Homepage",
      "dns_elapsed": 0.011,
      "ip": "52.57.149.77",
      "error_type": "VERY_SLOW",
      "double_scan_failed": false,
      "elapsed_real": 2.55
    },
    "screenshot": "https://raw.githubusercontent.com/dcs-masterclass-ia/stla-monitor/main/screenshots/Ford_FR_Homepage_20260705_235953.png",
    "is_reference": false
  },
  {
    "time": "06/07/2026 00:01:34",
    "brand": "Ford FR",
    "page": "Formulaire",
    "type": "ko",
    "detail": "Pas de réponse après 10.66s",
    "diagnostics": {
      "brand": "Ford FR",
      "page": "Formulaire",
      "dns_elapsed": 0.001,
      "ip": "52.57.149.77",
      "error_type": "VERY_SLOW",
      "double_scan_failed": false,
      "elapsed_real": 10.66
    },
    "screenshot": "https://raw.githubusercontent.com/dcs-masterclass-ia/stla-monitor/main/screenshots/Ford_FR_Formulaire_20260706_000205.png",
    "is_reference": false
  },
  {
    "time": "06/07/2026 00:01:34",
    "brand": "Ford FR",
    "page": "Homepage",
    "type": "ko",
    "detail": "Pas de réponse après 11.54s",
    "diagnostics": {
      "brand": "Ford FR",
      "page": "Homepage",
      "dns_elapsed": 0.004,
      "ip": "52.57.149.77",
      "error_type": "VERY_SLOW",
      "double_scan_failed": false,
      "elapsed_real": 11.54
    },
    "screenshot": "https://raw.githubusercontent.com/dcs-masterclass-ia/stla-monitor/main/screenshots/Ford_FR_Homepage_20260706_000218.png",
    "is_reference": false
  },
  {
    "time": "06/07/2026 00:03:10",
    "brand": "Ford FR",
    "page": "Formulaire",
    "type": "recovery",
    "detail": "Retour en ligne",
    "is_reference": false
  },
  {
    "time": "06/07/2026 00:03:10",
    "brand": "Ford FR",
    "page": "Homepage",
    "type": "recovery",
    "detail": "Retour en ligne",
    "is_reference": false
  },
  {
    "time": "06/07/2026 00:03:36",
    "brand": "Ford FR",
    "page": "Formulaire",
    "type": "ko",
    "detail": "Pas de réponse après 4.51s",
    "diagnostics": {
      "brand": "Ford FR",
      "page": "Formulaire",
      "dns_elapsed": 0.002,
      "ip": "63.186.28.171",
      "error_type": "VERY_SLOW",
      "double_scan_failed": false,
      "elapsed_real": 4.51
    },
    "screenshot": "https://raw.githubusercontent.com/dcs-masterclass-ia/stla-monitor/main/screenshots/Ford_FR_Formulaire_20260706_000400.png",
    "is_reference": false
  },
  {
    "time": "06/07/2026 00:03:36",
    "brand": "Ford FR",
    "page": "Homepage",
    "type": "ko",
    "detail": "Pas de réponse après 5.23s",
    "diagnostics": {
      "brand": "Ford FR",
      "page": "Homepage",
      "dns_elapsed": 0.004,
      "ip": "63.186.28.171",
      "error_type": "VERY_SLOW",
      "double_scan_failed": false,
      "elapsed_real": 5.23
    },
    "screenshot": "https://raw.githubusercontent.com/dcs-masterclass-ia/stla-monitor/main/screenshots/Ford_FR_Homepage_20260706_000414.png",
    "is_reference": false
  },
  {
    "time": "06/07/2026 00:04:32",
    "brand": "Ford FR",
    "page": "Formulaire",
    "type": "recovery",
    "detail": "Retour en ligne",
    "is_reference": false
  },
  {
    "time": "06/07/2026 00:04:32",
    "brand": "Ford FR",
    "page": "Homepage",
    "type": "recovery",
    "detail": "Retour en ligne",
    "is_reference": false
  },
  {
    "time": "06/07/2026 00:05:47",
    "brand": "Ford FR",
    "page": "Formulaire",
    "type": "ko",
    "detail": "Pas de réponse après 7.46s",
    "diagnostics": {
      "brand": "Ford FR",
      "page": "Formulaire",
      "dns_elapsed": 0.002,
      "ip": "63.186.144.32",
      "error_type": "VERY_SLOW",
      "double_scan_failed": false,
      "elapsed_real": 7.46
    },
    "screenshot": "https://raw.githubusercontent.com/dcs-masterclass-ia/stla-monitor/main/screenshots/Ford_FR_Formulaire_20260706_000622.png",
    "is_reference": false
  },
  {
    "time": "06/07/2026 00:05:47",
    "brand": "Ford FR",
    "page": "Homepage",
    "type": "ko",
    "detail": "Pas de réponse après 8.23s",
    "diagnostics": {
      "brand": "Ford FR",
      "page": "Homepage",
      "dns_elapsed": 0.004,
      "ip": "63.186.144.32",
      "error_type": "VERY_SLOW",
      "double_scan_failed": false,
      "elapsed_real": 8.23
    },
    "screenshot": "https://raw.githubusercontent.com/dcs-masterclass-ia/stla-monitor/main/screenshots/Ford_FR_Homepage_20260706_000628.png",
    "is_reference": false
  },
  {
    "time": "06/07/2026 00:07:23",
    "brand": "Ford FR",
    "page": "Formulaire",
    "type": "recovery",
    "detail": "Retour en ligne",
    "is_reference": false
  },
  {
    "time": "06/07/2026 00:07:23",
    "brand": "Ford FR",
    "page": "Homepage",
    "type": "recovery",
    "detail": "Retour en ligne",
    "is_reference": false
  },
  {
    "time": "06/07/2026 00:08:11",
    "brand": "Ford FR",
    "page": "Formulaire",
    "type": "ko",
    "detail": "Réponse lente : 7.6s (seuil 4s)",
    "diagnostics": {
      "brand": "Ford FR",
      "page": "Formulaire",
      "dns_elapsed": 0.001,
      "ip": "63.186.144.32",
      "http_status": 200,
      "elapsed_http": 7.6,
      "elapsed_total": 7.6,
      "redirect_count": 0,
      "final_url": "https://www.ford-reprise.fr/form",
      "headers": {
        "server": "—",
        "content-type": "text/html; charset=UTF-8",
        "x-cache": "—",
        "cf-ray": "—"
      },
      "error_type": "SLOW"
    },
    "screenshot": "https://raw.githubusercontent.com/dcs-masterclass-ia/stla-monitor/main/screenshots/Ford_FR_Formulaire_20260706_000831.png",
    "is_reference": false
  },
  {
    "time": "06/07/2026 00:08:11",
    "brand": "Ford FR",
    "page": "Homepage",
    "type": "ko",
    "detail": "Pas de réponse après 1.47s",
    "diagnostics": {
      "brand": "Ford FR",
      "page": "Homepage",
      "dns_elapsed": 0.007,
      "ip": "63.186.144.32",
      "error_type": "VERY_SLOW",
      "double_scan_failed": false,
      "elapsed_real": 1.47
    },
    "screenshot": "https://raw.githubusercontent.com/dcs-masterclass-ia/stla-monitor/main/screenshots/Ford_FR_Homepage_20260706_000844.png",
    "is_reference": false
  },
  {
    "time": "06/07/2026 00:09:36",
    "brand": "Ford FR",
    "page": "Formulaire",
    "type": "recovery",
    "detail": "Retour en ligne",
    "is_reference": false
  },
  {
    "time": "06/07/2026 00:09:36",
    "brand": "Ford FR",
    "page": "Homepage",
    "type": "recovery",
    "detail": "Retour en ligne",
    "is_reference": false
  }
]