[
  {
    "time": "20/06/2026 14:07:43",
    "brand": "Ford FR",
    "page": "Formulaire",
    "type": "ko",
    "detail": "Réponse très lente : 6.77s",
    "diagnostics": {
      "brand": "Ford FR",
      "page": "Formulaire",
      "dns_elapsed": 0.002,
      "ip": "63.180.121.144",
      "http_status": 200,
      "elapsed_http": 6.77,
      "elapsed_total": 6.77,
      "redirect_count": 0,
      "final_url": "https://www.ford-reprise.fr/form",
      "headers": {
        "server": "—",
        "content-type": "text/html; charset=UTF-8",
        "x-cache": "—",
        "cf-ray": "—"
      },
      "error_type": "VERY_SLOW"
    },
    "screenshot": "https://raw.githubusercontent.com/dcs-masterclass-ia/stla-monitor/main/screenshots/Ford_FR_Formulaire_20260620_140845.png",
    "is_reference": false
  },
  {
    "time": "20/06/2026 14:07:43",
    "brand": "Ford FR",
    "page": "Homepage",
    "type": "ko",
    "detail": "Réponse très lente : 7.14s",
    "diagnostics": {
      "brand": "Ford FR",
      "page": "Homepage",
      "dns_elapsed": 0.09,
      "ip": "63.180.121.144",
      "http_status": 200,
      "elapsed_http": 7.14,
      "elapsed_total": 7.23,
      "redirect_count": 0,
      "final_url": "https://www.ford-reprise.fr/",
      "headers": {
        "server": "—",
        "content-type": "text/html; charset=UTF-8",
        "x-cache": "—",
        "cf-ray": "—"
      },
      "error_type": "VERY_SLOW"
    },
    "screenshot": "https://raw.githubusercontent.com/dcs-masterclass-ia/stla-monitor/main/screenshots/Ford_FR_Homepage_20260620_140854.png",
    "is_reference": false
  },
  {
    "time": "20/06/2026 14:37:54",
    "brand": "Ford FR",
    "page": "Homepage",
    "type": "ko",
    "detail": "Pas de réponse après 8s",
    "diagnostics": {
      "brand": "Ford FR",
      "page": "Homepage",
      "dns_elapsed": 0.093,
      "ip": "3.69.153.2",
      "error_type": "TIMEOUT"
    },
    "screenshot": "https://raw.githubusercontent.com/dcs-masterclass-ia/stla-monitor/main/screenshots/Ford_FR_Homepage_20260620_143857.png",
    "is_reference": false
  }
]